tushare_docs_mcp/__init__.py
tushare_docs_mcp/main.py
tushare_docs_mcp/tools.py
tushare_docs_mcp/docs/tushare_basic.md
tushare_docs_mcp/docs/non-official/16_数据索引.md
tushare_docs_mcp/docs/non-official/17_社区捐助.md
tushare_docs_mcp/docs/non-official/catalog.md
tushare_docs_mcp/docs/non-official/01_股票数据/README.md
tushare_docs_mcp/docs/non-official/01_股票数据/01_基础数据/01_股票列表.md
tushare_docs_mcp/docs/non-official/01_股票数据/01_基础数据/02_每日股本（盘前）.md
tushare_docs_mcp/docs/non-official/01_股票数据/01_基础数据/03_交易日历.md
tushare_docs_mcp/docs/non-official/01_股票数据/01_基础数据/04_ST股票列表.md
tushare_docs_mcp/docs/non-official/01_股票数据/01_基础数据/05_沪深港通股票列表.md
tushare_docs_mcp/docs/non-official/01_股票数据/01_基础数据/06_股票曾用名.md
tushare_docs_mcp/docs/non-official/01_股票数据/01_基础数据/07_上市公司基本信息.md
tushare_docs_mcp/docs/non-official/01_股票数据/01_基础数据/08_上市公司管理层.md
tushare_docs_mcp/docs/non-official/01_股票数据/01_基础数据/09_管理层薪酬和持股.md
tushare_docs_mcp/docs/non-official/01_股票数据/01_基础数据/10_北交所新旧代码对照.md
tushare_docs_mcp/docs/non-official/01_股票数据/01_基础数据/11_IPO新股上市.md
tushare_docs_mcp/docs/non-official/01_股票数据/01_基础数据/12_股票历史列表.md
tushare_docs_mcp/docs/non-official/01_股票数据/01_基础数据/README.md
tushare_docs_mcp/docs/non-official/01_股票数据/02_行情数据/01_历史日线.md
tushare_docs_mcp/docs/non-official/01_股票数据/02_行情数据/02_实时K线.md
tushare_docs_mcp/docs/non-official/01_股票数据/02_行情数据/03_历史分钟.md
tushare_docs_mcp/docs/non-official/01_股票数据/02_行情数据/04_实时分钟.md
tushare_docs_mcp/docs/non-official/01_股票数据/02_行情数据/05_周线行情.md
tushare_docs_mcp/docs/non-official/01_股票数据/02_行情数据/06_月线行情.md
tushare_docs_mcp/docs/non-official/01_股票数据/02_行情数据/07_复权行情.md
tushare_docs_mcp/docs/non-official/01_股票数据/02_行情数据/08_周_月线行情_每日更新.md
tushare_docs_mcp/docs/non-official/01_股票数据/02_行情数据/09_周_月线复权行情_每日更新.md
tushare_docs_mcp/docs/non-official/01_股票数据/02_行情数据/10_复权因子.md
tushare_docs_mcp/docs/non-official/01_股票数据/02_行情数据/11_实时Tick（爬虫）.md
tushare_docs_mcp/docs/non-official/01_股票数据/02_行情数据/12_实时成交（爬虫）.md
tushare_docs_mcp/docs/non-official/01_股票数据/02_行情数据/13_实时排名（爬虫）.md
tushare_docs_mcp-0.1.0.dist-info/METADATA
tushare_docs_mcp-0.1.0.dist-info/WHEEL
tushare_docs_mcp-0.1.0.dist-info/entry_points.txt
tushare_docs_mcp-0.1.0.dist-info/licenses/LICENSE
tushare_docs_mcp-0.1.0.dist-info/RECORD
