Metadata-Version: 2.4
Name: tushare-docs-mcp
Version: 0.1.0
Summary: Tushare Docs MCP Server - 提供Tushare接口文档查询功能
Project-URL: Homepage, https://github.com/momojie/tushare-docs-mcp
Project-URL: Repository, https://github.com/momojie/tushare-docs-mcp.git
Project-URL: Issues, https://github.com/momojie/tushare-docs-mcp/issues
Author-email: Momojie <momojiesuper@gmail.com>
License: MIT
License-File: LICENSE
Classifier: Development Status :: 4 - Beta
Classifier: Intended Audience :: Developers
Classifier: License :: OSI Approved :: MIT License
Classifier: Programming Language :: Python :: 3
Classifier: Programming Language :: Python :: 3.11
Classifier: Programming Language :: Python :: 3.12
Classifier: Programming Language :: Python :: 3.13
Classifier: Topic :: Documentation
Classifier: Topic :: Software Development :: Libraries :: Python Modules
Requires-Python: >=3.11
Requires-Dist: mcp>=1.15.0
